setup.py
googler/__init__.py
googler.egg-info/PKG-INFO
googler.egg-info/SOURCES.txt
googler.egg-info/dependency_links.txt
googler.egg-info/requires.txt
googler.egg-info/top_level.txt
googler/maps/__init__.py
googler/maps/geocoding.py
googler/maps/tests/__init__.py
googler/maps/tests/test_geocode_parse.py
googler/recaptcha/__init__.py
googler/recaptcha/captcha.py
googler/recaptcha/captcha2.py
googler/recaptcha/mailhide.py
googler/recaptcha/tests/__init__.py
googler/recaptcha/tests/test_captcha2.py
googler/recaptcha/tests/test_encryption.py
googler/utils/__init__.py
googler/utils/compat.py
googler/utils/http.py