Metadata-Version: 1.1
Name: googler
Version: 1.0.1
Summary: Google API Library for Python
Home-page: https://github.com/commx/googler
Author: Christian Jurk
Author-email: commx@commx.ws
License: Apache
Keywords: google api recaptcha geocode geocoding
Platform: UNKNOWN
Classifier: Development Status :: 4 - Beta
Classifier: License :: OSI Approved :: Apache Software License
Classifier: Programming Language :: Python
Classifier: Programming Language :: Python :: 2.6
Classifier: Programming Language :: Python :: 2.7
Classifier: Programming Language :: Python :: 3.3
Classifier: Programming Language :: Python :: 3.4
Classifier: Topic :: Software Development :: Libraries
